Metadata-Version: 2.4
Name: text2mcp
Version: 0.2.9
Summary: Generate MCP services from natural language descriptions
Author-email: ooooofish <ooooofish@126.com>
License: MIT
Project-URL: Homepage, https://github.com/whillhill/text2mcp
Project-URL: Bug Tracker, https://github.com/whillhill/text2mcp/issues
Classifier: Programming Language :: Python :: 3
Classifier: Programming Language :: Python :: 3.8
Classifier: Programming Language :: Python :: 3.9
Classifier: Programming Language :: Python :: 3.10
Classifier: License :: OSI Approved :: MIT License
Classifier: Operating System :: OS Independent
Requires-Python: >=3.8
License-File: LICENSE
Requires-Dist: uvicorn>=0.15.0
Requires-Dist: fastapi>=0.68.0
Requires-Dist: starlette>=0.14.2
Requires-Dist: pydantic>=1.8.2
Requires-Dist: toml>=0.10.2
Requires-Dist: python-dotenv>=0.19.0
Requires-Dist: openai>=1.0.0
Requires-Dist: mcp>=1.9.0
Requires-Dist: PyYAML>=6.0
Provides-Extra: dev
Requires-Dist: pytest>=6.0; extra == "dev"
Requires-Dist: black>=21.5b2; extra == "dev"
Requires-Dist: isort>=5.9.1; extra == "dev"
Requires-Dist: mypy>=0.812; extra == "dev"
Requires-Dist: flake8>=3.9.2; extra == "dev"
Dynamic: license-file
